quickpack.py
quickpack-0.0.2.dist-info/METADATA
quickpack-0.0.2.dist-info/WHEEL
quickpack-0.0.2.dist-info/entry_points.txt
quickpack-0.0.2.dist-info/top_level.txt
quickpack-0.0.2.dist-info/RECORD
